<?xml version="1.0" encoding="UTF-8" standalone="yes"?>
<comments xmlns="http://schemas.openxmlformats.org/spreadsheetml/2006/main" xmlns:mc="http://schemas.openxmlformats.org/markup-compatibility/2006" mc:Ignorable="xr" xmlns:xr="http://schemas.microsoft.com/office/spreadsheetml/2014/revision"><authors><author>Meu Computador</author><author>Romerio</author></authors><commentList><comment ref="I1" authorId="0" shapeId="0" xr:uid="{5F4F7D59-2DF5-4CFF-981D-9A1632FBE5CA}"><text><r><rPr><b/><sz val="9"/><color indexed="81"/><rFont val="Tahoma"/><family val="2"/></rPr><t xml:space="preserve">Eliz:Salário+HE/12
</t></r></text></comment><comment ref="K1" authorId="0" shapeId="0" xr:uid="{80297928-F694-47FC-A654-62C3FDE603D6}"><text><r><rPr><b/><sz val="9"/><color indexed="81"/><rFont val="Tahoma"/><family val="2"/></rPr><t>Eliz:Soma-se c+d+e+f+g+h*2.7% é a participação da empresa ao INSS do empregado.</t></r><r><rPr><sz val="9"/><color indexed="81"/><rFont val="Tahoma"/><family val="2"/></rPr><t xml:space="preserve">
</t></r></text></comment><comment ref="L1" authorId="0" shapeId="0" xr:uid="{00F58CD8-9B98-43F4-8F7D-2502A9728AFB}"><text><r><rPr><b/><sz val="9"/><color indexed="81"/><rFont val="Tahoma"/><family val="2"/></rPr><t xml:space="preserve">Eliz:c+d+e+f+g*8% </t></r><r><rPr><sz val="9"/><color indexed="81"/><rFont val="Tahoma"/><family val="2"/></rPr><t xml:space="preserve">
</t></r></text></comment><comment ref="B18" authorId="1" shapeId="0" xr:uid="{F76ED94A-929E-4E28-BC49-BB336D9F80D6}"><text><r><rPr><b/><sz val="9"/><color indexed="81"/><rFont val="Segoe UI"/><family val="2"/></rPr><t>Romerio:</t></r><r><rPr><sz val="9"/><color indexed="81"/><rFont val="Segoe UI"/><family val="2"/></rPr><t xml:space="preserve">
30% de custo mensal da agroinvest 
</t></r></text></comment></commentList></comments>